zengrad/__init__.py
zengrad/zengrad.py
zengrad-1.0.8.dist-info/METADATA
zengrad-1.0.8.dist-info/WHEEL
zengrad-1.0.8.dist-info/top_level.txt
zengrad-1.0.8.dist-info/RECORD
